{
  "id": "fab70e30-ebc1-43ad-9a3b-d76c32fc1e58",
  "prevId": "f12e213f-eb13-469e-935c-77708608d418",
  "version": "5",
  "dialect": "sqlite",
  "tables": {
    "recipe_image": {
      "name": "recipe_image",
      "columns": {
        "id": {
          "name": "id",
          "type": "integer",
          "primaryKey": true,
          "notNull": true,
          "autoincrement": true
        },
        "recipe_id": {
          "name": "recipe_id",
          "type": "integer",
          "primaryKey": false,
          "notNull": true,
          "autoincrement": false
        },
        "url": {
          "name": "url",
          "type": "text",
          "primaryKey": false,
          "notNull": true,
          "autoincrement": false
        },
        "created_at": {
          "name": "created_at",
          "type": "text",
          "primaryKey": false,
          "notNull": false,
          "autoincrement": false,
          "default": "CURRENT_TIMESTAMP"
        },
        "updated_at": {
          "name": "updated_at",
          "type": "text",
          "primaryKey": false,
          "notNull": false,
          "autoincrement": false,
          "default": "CURRENT_TIMESTAMP"
        }
      },
      "indexes": {},
      "foreignKeys": {
        "recipe_image_recipe_id_recipe_id_fk": {
          "name": "recipe_image_recipe_id_recipe_id_fk",
          "tableFrom": "recipe_image",
          "columnsFrom": [
            "recipe_id"
          ],
          "tableTo": "recipe",
          "columnsTo": [
            "id"
          ],
          "onUpdate": "no action",
          "onDelete": "cascade"
        }
      },
      "compositePrimaryKeys": {},
      "uniqueConstraints": {}
    },
    "recipe_ingredient": {
      "name": "recipe_ingredient",
      "columns": {
        "id": {
          "name": "id",
          "type": "integer",
          "primaryKey": true,
          "notNull": true,
          "autoincrement": true
        },
        "recipe_id": {
          "name": "recipe_id",
          "type": "integer",
          "primaryKey": false,
          "notNull": true,
          "autoincrement": false
        },
        "ingredient": {
          "name": "ingredient",
          "type": "text",
          "primaryKey": false,
          "notNull": true,
          "autoincrement": false
        },
        "created_at": {
          "name": "created_at",
          "type": "text",
          "primaryKey": false,
          "notNull": false,
          "autoincrement": false,
          "default": "CURRENT_TIMESTAMP"
        },
        "updated_at": {
          "name": "updated_at",
          "type": "text",
          "primaryKey": false,
          "notNull": false,
          "autoincrement": false,
          "default": "CURRENT_TIMESTAMP"
        }
      },
      "indexes": {},
      "foreignKeys": {
        "recipe_ingredient_recipe_id_recipe_id_fk": {
          "name": "recipe_ingredient_recipe_id_recipe_id_fk",
          "tableFrom": "recipe_ingredient",
          "columnsFrom": [
            "recipe_id"
          ],
          "tableTo": "recipe",
          "columnsTo": [
            "id"
          ],
          "onUpdate": "no action",
          "onDelete": "cascade"
        }
      },
      "compositePrimaryKeys": {},
      "uniqueConstraints": {}
    },
    "recipe_step": {
      "name": "recipe_step",
      "columns": {
        "id": {
          "name": "id",
          "type": "integer",
          "primaryKey": true,
          "notNull": true,
          "autoincrement": true
        },
        "recipe_id": {
          "name": "recipe_id",
          "type": "integer",
          "primaryKey": false,
          "notNull": true,
          "autoincrement": false
        },
        "step": {
          "name": "step",
          "type": "text",
          "primaryKey": false,
          "notNull": true,
          "autoincrement": false
        },
        "step_number": {
          "name": "step_number",
          "type": "integer",
          "primaryKey": false,
          "notNull": true,
          "autoincrement": false
        },
        "created_at": {
          "name": "created_at",
          "type": "text",
          "primaryKey": false,
          "notNull": false,
          "autoincrement": false,
          "default": "CURRENT_TIMESTAMP"
        },
        "updated_at": {
          "name": "updated_at",
          "type": "text",
          "primaryKey": false,
          "notNull": false,
          "autoincrement": false,
          "default": "CURRENT_TIMESTAMP"
        }
      },
      "indexes": {},
      "foreignKeys": {
        "recipe_step_recipe_id_recipe_id_fk": {
          "name": "recipe_step_recipe_id_recipe_id_fk",
          "tableFrom": "recipe_step",
          "columnsFrom": [
            "recipe_id"
          ],
          "tableTo": "recipe",
          "columnsTo": [
            "id"
          ],
          "onUpdate": "no action",
          "onDelete": "cascade"
        }
      },
      "compositePrimaryKeys": {},
      "uniqueConstraints": {}
    },
    "recipe_tag": {
      "name": "recipe_tag",
      "columns": {
        "id": {
          "name": "id",
          "type": "integer",
          "primaryKey": true,
          "notNull": true,
          "autoincrement": true
        },
        "recipe_id": {
          "name": "recipe_id",
          "type": "integer",
          "primaryKey": false,
          "notNull": true,
          "autoincrement": false
        },
        "tag": {
          "name": "tag",
          "type": "text",
          "primaryKey": false,
          "notNull": true,
          "autoincrement": false
        },
        "created_at": {
          "name": "created_at",
          "type": "text",
          "primaryKey": false,
          "notNull": false,
          "autoincrement": false,
          "default": "CURRENT_TIMESTAMP"
        },
        "updated_at": {
          "name": "updated_at",
          "type": "text",
          "primaryKey": false,
          "notNull": false,
          "autoincrement": false,
          "default": "CURRENT_TIMESTAMP"
        }
      },
      "indexes": {},
      "foreignKeys": {
        "recipe_tag_recipe_id_recipe_id_fk": {
          "name": "recipe_tag_recipe_id_recipe_id_fk",
          "tableFrom": "recipe_tag",
          "columnsFrom": [
            "recipe_id"
          ],
          "tableTo": "recipe",
          "columnsTo": [
            "id"
          ],
          "onUpdate": "no action",
          "onDelete": "cascade"
        }
      },
      "compositePrimaryKeys": {},
      "uniqueConstraints": {}
    },
    "recipe": {
      "name": "recipe",
      "columns": {
        "id": {
          "name": "id",
          "type": "integer",
          "primaryKey": true,
          "notNull": true,
          "autoincrement": true
        },
        "title": {
          "name": "title",
          "type": "text",
          "primaryKey": false,
          "notNull": true,
          "autoincrement": false
        },
        "description": {
          "name": "description",
          "type": "text",
          "primaryKey": false,
          "notNull": true,
          "autoincrement": false
        },
        "slug": {
          "name": "slug",
          "type": "text",
          "primaryKey": false,
          "notNull": true,
          "autoincrement": false
        },
        "prep_time": {
          "name": "prep_time",
          "type": "integer",
          "primaryKey": false,
          "notNull": false,
          "autoincrement": false
        },
        "cook_time": {
          "name": "cook_time",
          "type": "integer",
          "primaryKey": false,
          "notNull": false,
          "autoincrement": false
        },
        "servings": {
          "name": "servings",
          "type": "integer",
          "primaryKey": false,
          "notNull": false,
          "autoincrement": false
        },
        "created_at": {
          "name": "created_at",
          "type": "text",
          "primaryKey": false,
          "notNull": false,
          "autoincrement": false,
          "default": "CURRENT_TIMESTAMP"
        },
        "updated_at": {
          "name": "updated_at",
          "type": "text",
          "primaryKey": false,
          "notNull": false,
          "autoincrement": false,
          "default": "CURRENT_TIMESTAMP"
        }
      },
      "indexes": {
        "recipe_title_unique": {
          "name": "recipe_title_unique",
          "columns": [
            "title"
          ],
          "isUnique": true
        },
        "recipe_slug_unique": {
          "name": "recipe_slug_unique",
          "columns": [
            "slug"
          ],
          "isUnique": true
        }
      },
      "foreignKeys": {},
      "compositePrimaryKeys": {},
      "uniqueConstraints": {}
    },
    "user": {
      "name": "user",
      "columns": {
        "id": {
          "name": "id",
          "type": "integer",
          "primaryKey": true,
          "notNull": true,
          "autoincrement": true
        },
        "email": {
          "name": "email",
          "type": "text",
          "primaryKey": false,
          "notNull": true,
          "autoincrement": false
        },
        "password": {
          "name": "password",
          "type": "text",
          "primaryKey": false,
          "notNull": true,
          "autoincrement": false
        },
        "user_type": {
          "name": "user_type",
          "type": "text",
          "primaryKey": false,
          "notNull": true,
          "autoincrement": false
        },
        "created_at": {
          "name": "created_at",
          "type": "text",
          "primaryKey": false,
          "notNull": false,
          "autoincrement": false,
          "default": "CURRENT_TIMESTAMP"
        },
        "updated_at": {
          "name": "updated_at",
          "type": "text",
          "primaryKey": false,
          "notNull": false,
          "autoincrement": false,
          "default": "CURRENT_TIMESTAMP"
        }
      },
      "indexes": {
        "user_email_unique": {
          "name": "user_email_unique",
          "columns": [
            "email"
          ],
          "isUnique": true
        }
      },
      "foreignKeys": {},
      "compositePrimaryKeys": {},
      "uniqueConstraints": {}
    }
  },
  "enums": {},
  "_meta": {
    "columns": {},
    "schemas": {},
    "tables": {}
  }
}